korth_spirit/__init__.py
korth_spirit/configuration/__init__.py
korth_spirit/configuration/aggregate_configuration.py
korth_spirit/configuration/configuration.py
korth_spirit/configuration/environment_configuration.py
korth_spirit/configuration/input_configuration.py
korth_spirit/configuration/json_configuration.py
korth_spirit/data/__init__.py
korth_spirit/data/address_data.py
korth_spirit/data/attribute_data.py
korth_spirit/data/bot_menu_data.py
korth_spirit/data/camera_set_data.py
korth_spirit/data/cav_change_data.py
korth_spirit/data/cav_delete_data.py
korth_spirit/data/cell_iterator_data.py
korth_spirit/data/cell_object_data.py
korth_spirit/data/citizen_data.py
korth_spirit/data/console_message_data.py
korth_spirit/data/hud_click_data.py
korth_spirit/data/hud_data.py
korth_spirit/data/laser_beam_data.py
korth_spirit/data/license_change_data.py
korth_spirit/data/license_create_data.py
korth_spirit/data/license_data.py
korth_spirit/data/login_data.py
korth_spirit/data/object_bump_data.py
korth_spirit/data/object_change_data.py
korth_spirit/data/object_click_data.py
korth_spirit/data/object_clicked_data.py
korth_spirit/data/object_create_data.py
korth_spirit/data/object_created_data.py
korth_spirit/data/object_delete_data.py
korth_spirit/data/object_load_data.py
korth_spirit/data/object_loaded_data.py
korth_spirit/data/object_queried_data.py
korth_spirit/data/object_query_data.py
korth_spirit/data/server_data.py
korth_spirit/data/server_return_data.py
korth_spirit/data/state_change_data.py
korth_spirit/data/terrain_node_data.py
korth_spirit/events/__init__.py
korth_spirit/events/bus.py
korth_spirit/events/event.py
korth_spirit/events/translations.py
korth_spirit/instance/__init__.py
korth_spirit/instance/configurable_instance.py
korth_spirit/instance/instance.py
korth_spirit/query/__init__.py
korth_spirit/query/objects.py
korth_spirit/query/query.py
korth_spirit/query/query_enum.py
korth_spirit/query/query_factory.py
korth_spirit/query/terrain.py
korth_spirit-0.0.119.dist-info/LICENSE
korth_spirit-0.0.119.dist-info/METADATA
korth_spirit-0.0.119.dist-info/WHEEL
korth_spirit-0.0.119.dist-info/top_level.txt
korth_spirit-0.0.119.dist-info/RECORD
