Metadata-Version: 2.1
Name: korth-spirit
Version: 0.0.119
Summary: Python Wrapper for the Active Worlds Software Development Kit (SDK)
Home-page: https://github.com/Korth-Spirit/Korth-Spirit
Author: Johnathan Irvin
Author-email: irvinjohnathan@gmail.com
Project-URL: Bug Tracker, https://github.com/Korth-Spirit/Korth-Spirit/issues
Classifier: Programming Language :: Python :: 3
Classifier: License :: OSI Approved :: MIT License
Classifier: Operating System :: OS Independent
Requires-Python: >=3.6
License-File: LICENSE
